worktimer/__init__.py
worktimer/cli/__init__.py
worktimer/cli/cli.py
worktimer/cli/commands/__init__.py
worktimer/cli/commands/day.py
worktimer/cli/commands/start.py
worktimer/cli/commands/stop.py
worktimer/cli/commands/util.py
worktimer/cli/commands/week.py
worktimer/cli/main.py
worktimer/core/__init__.py
worktimer/core/const.py
worktimer/core/database.py
worktimer/core/util.py
worktimer/core/worktimer.py
worktimer-1.0.0.dist-info/LICENSE
worktimer-1.0.0.dist-info/METADATA
worktimer-1.0.0.dist-info/WHEEL
worktimer-1.0.0.dist-info/entry_points.txt
worktimer-1.0.0.dist-info/RECORD
