Metadata-Version: 2.3
Name: worktimer
Version: 1.0.0
Summary: Simple tracker of time spent on the job
License: MIT
Author: truthless-dev
Author-email: truthless.deviant248@simplelogin.fr
Requires-Python: >=3.11,<4.0
Classifier: License :: OSI Approved :: MIT License
Classifier: Programming Language :: Python :: 3
Classifier: Programming Language :: Python :: 3.11
Classifier: Programming Language :: Python :: 3.12
Classifier: Programming Language :: Python :: 3.13
Requires-Dist: click (>=8.2.1,<9.0.0)
